RoSE/__init__.py
RoSE/rose.py
RoSE/utils.py
rotary_spatial_embeddings-2025.9.27.2133.dist-info/METADATA
rotary_spatial_embeddings-2025.9.27.2133.dist-info/WHEEL
rotary_spatial_embeddings-2025.9.27.2133.dist-info/licenses/LICENSE
rotary_spatial_embeddings-2025.9.27.2133.dist-info/RECORD
